default_profile.py
awsume_default_profile_plugin-0.1.0.dist-info/LICENSE
awsume_default_profile_plugin-0.1.0.dist-info/METADATA
awsume_default_profile_plugin-0.1.0.dist-info/WHEEL
awsume_default_profile_plugin-0.1.0.dist-info/entry_points.txt
awsume_default_profile_plugin-0.1.0.dist-info/top_level.txt
awsume_default_profile_plugin-0.1.0.dist-info/RECORD
