Metadata-Version: 2.1
Name: awsume-default-profile-plugin
Version: 0.1.0
Summary: This is a plugin for awsume that allows you to configure the default profile.
Home-page: https://github.com/rdimartino/awsume-default-profile-plugin
Author: Robert DiMartino
Author-email: robert@dimartino.dev
License: MIT
Platform: UNKNOWN
